saltext/freezer/__init__.py
saltext/freezer/version.py
saltext/freezer/modules/__init__.py
saltext/freezer/modules/freezer.py
saltext/freezer/states/__init__.py
saltext.freezer-1.0.0.dist-info/LICENSE
saltext.freezer-1.0.0.dist-info/METADATA
saltext.freezer-1.0.0.dist-info/WHEEL
saltext.freezer-1.0.0.dist-info/entry_points.txt
saltext.freezer-1.0.0.dist-info/top_level.txt
saltext.freezer-1.0.0.dist-info/RECORD
